Workbook
Name aporte: Planilha1!$D$9
Name patrimonio: Planilha1!$D$12
Name qtd_anos: Planilha1!$D$10
Name Rendimento_carteira: Planilha1!$D$5
Name salario: Planilha1!$D$4
Name taxa_mensal: Planilha1!$D$11

Sheet Planilha3

Sheet Planilha1
B1: DIO INVEST- BeatrizVCosta
B3: Configurações
B4: Salário | D4: 4200
B5: Rendimento Carteira | D5: 0.0089
B6: Sugestão de investimento(30%) | D6: =D4*30% -> 1260
B8: Investimento mensal
B9: Quanto investir por mês? | D9: 1260
B10: Por quantos anos? | D10: 10
B11: Taxa de rendimento mensal? | D11: 0.01079
B12: Patrimonio acumulado? | D12: =FV(taxa_mensal,qtd_anos*12,-aporte) -> 306538.11
B13: Dividendos mensais? | D13: =patrimonio*Rendimento_carteira -> 2728.1892
B16: Cenários | D16: Dividendo
A17: 2 | B17: Quanto em 2 anos? | C17: =FV($D$11,$A17*12,-$D$9) -> 34306.81 | D17: =C17*Rendimento_carteira -> 305.33061
A18: 5 | B18: Quanto em 5 anos? | C18: =FV($D$11,$A18*12,-$D$9) -> 105558.91 | D18: =C18*Rendimento_carteira -> 939.47431
A19: 10 | B19: Quanto em 10 anos? | C19: =FV($D$11,$A19*12,-$D$9) -> 306538.11 | D19: =C19*Rendimento_carteira -> 2728.1892
A20: 20 | B20: Quanto em 20 anos? | C20: =FV($D$11,$A20*12,-$D$9) -> 1417750 | D20: =C20*Rendimento_carteira -> 12617.975
A21: 30 | B21: Quanto em 30 anos? | C21: =FV($D$11,$A21*12,-$D$9) -> 5445933.8 | D21: =C21*Rendimento_carteira -> 48468.811
B25: Perfil | C25: Moderado
B26: VALOR A SER INVESTIDO POR MÊS | C26: =aporte -> 1260
B29: TIPO DE FII | C29: Percentual Sugerido | D29: Valores
B30: PAPEL | C30: =VLOOKUP($C$25&"-"&B30,Planilha2!$A$1:$D$19,4,) -> 0.32 | D30: =C30*$C$26 -> 403.2
B31: TIJOLO | C31: =VLOOKUP($C$25&"-"&B31,Planilha2!$A$1:$D$19,4,) -> 0.4 | D31: =C31*$C$26 -> 504
B32: HÍBRIDOS | C32: =VLOOKUP($C$25&"-"&B32,Planilha2!$A$1:$D$19,4,) -> 0.08 | D32: =C32*$C$26 -> 100.8
B33: FOFs | C33: =VLOOKUP($C$25&"-"&B33,Planilha2!$A$1:$D$19,4,) -> 0.1 | D33: =C33*$C$26 -> 126
B34: DESENVOLVIMENTO | C34: =VLOOKUP($C$25&"-"&B34,Planilha2!$A$1:$D$19,4,) -> 0.1 | D34: =C34*$C$26 -> 126
B35: HOTELARIAS | C35: =VLOOKUP($C$25&"-"&B35,Planilha2!$A$1:$D$19,4,) -> 0.1 | D35: =C35*$C$26 -> 126

Sheet Planilha2
A1: CHAVE | B1: PERFIL | C1: TIPO DE FII | D1: %
A2: =B2&"-"&C2 -> Conservador-PAPEL | B2: Conservador | C2: PAPEL | D2: 0.3
A3: =B3&"-"&C3 -> Conservador-TIJOLO | B3: Conservador | C3: TIJOLO | D3: 0.5
A4: =B4&"-"&C4 -> Conservador-HÍBRIDOS | B4: Conservador | C4: HÍBRIDOS | D4: 0.1 | G4: Moderado-TIJOLO | H4: =VLOOKUP(G4,$A$1:$D$19,4,) -> 0.4
A5: =B5&"-"&C5 -> Conservador-FOFs | B5: Conservador | C5: FOFs | D5: 0.1
A6: =B6&"-"&C6 -> Conservador-DESENVOLVIMENTO | B6: Conservador | C6: DESENVOLVIMENTO | D6: 0
A7: =B7&"-"&C7 -> Conservador-HOTELARIAS | B7: Conservador | C7: HOTELARIAS | D7: 0
A8: =B8&"-"&C8 -> Moderado-PAPEL | B8: Moderado | C8: PAPEL | D8: 0.32
A9: =B9&"-"&C9 -> Moderado-TIJOLO | B9: Moderado | C9: TIJOLO | D9: 0.4
A10: =B10&"-"&C10 -> Moderado-HÍBRIDOS | B10: Moderado | C10: HÍBRIDOS | D10: 0.08
A11: =B11&"-"&C11 -> Moderado-FOFs | B11: Moderado | C11: FOFs | D11: 0.1
A12: =B12&"-"&C12 -> Moderado-DESENVOLVIMENTO | B12: Moderado | C12: DESENVOLVIMENTO | D12: 0.1
A13: =B13&"-"&C13 -> Moderado-HOTELARIAS | B13: Moderado | C13: HOTELARIAS | D13: 0.1
A14: =B14&"-"&C14 -> Agressivo-PAPEL | B14: Agressivo | C14: PAPEL | D14: 0.5
A15: =B15&"-"&C15 -> Agressivo-TIJOLO | B15: Agressivo | C15: TIJOLO | D15: 0.1
A16: =B16&"-"&C16 -> Agressivo-HÍBRIDOS | B16: Agressivo | C16: HÍBRIDOS | D16: 0.05
... A19: =B19&"-"&C19 -> Agressivo-HOTELARIAS | B19: Agressivo | C19: HOTELARIAS | D19: 0.1
